slack_api_decorator/__init__.py
slack_api_decorator/error.py
slack_api_decorator/event_subscription.py
slack_api_decorator/slash_command.py
slack_api_decorator/utils.py
test/__init__.py
test/conftest.py
test/test_event_subscription.py
test/test_slash_command.py
test/test_utils.py
slackapidecorator-0.2.0.dist-info/METADATA
slackapidecorator-0.2.0.dist-info/WHEEL
slackapidecorator-0.2.0.dist-info/top_level.txt
slackapidecorator-0.2.0.dist-info/RECORD
