Metadata-Version: 2.1
Name: slackapidecorator
Version: 0.2.0
Summary: slack api decorator
Home-page: https://github.com/gsy0911/slack-api-decorator
Author: gsy0911
Author-email: yoshiki0911@gmail.com
License: MIT
Keywords: slack,slack-api,slash-command,event-subscription
Platform: UNKNOWN
Classifier: Programming Language :: Python :: 3
Classifier: Programming Language :: Python :: 3.8
Classifier: Programming Language :: Python :: 3.9
Classifier: Development Status :: 3 - Alpha
Classifier: Operating System :: OS Independent
Classifier: Intended Audience :: Developers
Classifier: License :: OSI Approved :: MIT License
Requires-Python: >=3.8
